userland/__init__.py
userland/__main__.py
userland/core/__init__.py
userland/core/command.py
userland/core/io.py
userland/core/paths.py
userland/core/users.py
userland/utilities/__init__.py
userland/utilities/basename.py
userland/utilities/cat.py
userland/utilities/chgrp.py
userland/utilities/chown.py
userland/utilities/clear.py
userland/utilities/cut.py
userland/utilities/dirname.py
userland/utilities/echo.py
userland/utilities/env.py
userland/utilities/factor.py
userland/utilities/false.py
userland/utilities/groups.py
userland/utilities/hostid.py
userland/utilities/id.py
userland/utilities/logname.py
userland/utilities/nologin.py
userland/utilities/nproc.py
userland/utilities/printenv.py
userland/utilities/pwd.py
userland/utilities/readlink.py
userland/utilities/realpath.py
userland/utilities/reset.py
userland/utilities/seq.py
userland/utilities/sleep.py
userland/utilities/sum.py
userland/utilities/sync.py
userland/utilities/true.py
userland/utilities/truncate.py
userland/utilities/tty.py
userland/utilities/uname.py
userland/utilities/whoami.py
userland/utilities/yes.py
userland-0.1.0.dist-info/licenses/LICENSE
userland-0.1.0.dist-info/METADATA
userland-0.1.0.dist-info/WHEEL
userland-0.1.0.dist-info/entry_points.txt
userland-0.1.0.dist-info/top_level.txt
userland-0.1.0.dist-info/RECORD
