Metadata-Version: 2.4
Name: userland
Version: 0.1.0
Summary: Various Unix and Linux utilities in Python!
Author-email: Expertcoderz <expertcoderzx@gmail.com>
License-Expression: GPL-3.0-or-later
Project-URL: Homepage, https://github.com/Expertcoderz/python-userland
Project-URL: Repository, https://github.com/Expertcoderz/python-userland.git
Project-URL: Issues, https://github.com/Expertcoderz/python-userland/issues
Classifier: Development Status :: 2 - Pre-Alpha
Classifier: Environment :: Console
Classifier: Intended Audience :: Developers
Classifier: Intended Audience :: End Users/Desktop
Classifier: Intended Audience :: System Administrators
Classifier: Operating System :: OS Independent
Classifier: Operating System :: POSIX
Classifier: Programming Language :: Python :: 3.13
Classifier: Programming Language :: Python :: 3 :: Only
Classifier: Topic :: System :: Software Distribution
Requires-Python: >=3.13
License-File: LICENSE
Requires-Dist: tqdm>=4.67.1
Dynamic: license-file
